{
  "event_id": "42cd2c9d9860ded679366dcdfe136ea7",
  "sport_key": "baseball_mlb",
  "home_team": "Detroit Tigers",
  "away_team": "Boston Red Sox",
  "commence_time": "2026-05-04T22:41:00Z",
  "snapshots": [
    {
      "timestamp": "2026-05-03_22-26-25",
      "hours_to_game": 24.230824105277776,
      "h2h": {
        "Boston Red Sox": {
          "fanduel": 190,
          "fanatics": 185,
          "unibet_fr": 160,
          "sport888": 185,
          "winamax_fr": 155,
          "mybookieag": 183,
          "nordicbet": 184,
          "winamax_de": 175,
          "betsson": 184,
          "onexbet": 192,
          "williamhill": 175,
          "marathonbet": 183,
          "draftkings": 179,
          "pinnacle": 194,
          "bovada": 190,
          "betrivers": 180,
          "unibet_se": 185,
          "leovegas_se": 180,
          "unibet_nl": 185
        },
        "Detroit Tigers": {
          "fanduel": -230,
          "fanatics": -225,
          "unibet_fr": -250,
          "sport888": -250,
          "winamax_fr": -256,
          "mybookieag": -217,
          "nordicbet": -233,
          "winamax_de": -227,
          "betsson": -233,
          "onexbet": -211,
          "williamhill": -225,
          "marathonbet": -233,
          "draftkings": -219,
          "pinnacle": -220,
          "bovada": -230,
          "betrivers": -230,
          "unibet_se": -225,
          "leovegas_se": -225,
          "unibet_nl": -225
        }
      },
      "spreads": {
        "Boston Red Sox": {
          "fanduel": {
            "line": 1.5,
            "price": -118
          },
          "fanatics": {
            "line": 1.5,
            "price": -125
          },
          "sport888": {
            "line": 1.5,
            "price": -125
          },
          "mybookieag": {
            "line": 1.5,
            "price": -120
          },
          "nordicbet": {
            "line": 1.5,
            "price": -125
          },
          "betsson": {
            "line": 1.5,
            "price": -125
          },
          "onexbet": {
            "line": 1.5,
            "price": -121
          },
          "draftkings": {
            "line": 1.5,
            "price": -122
          },
          "pinnacle": {
            "line": 1.5,
            "price": -120
          },
          "bovada": {
            "line": 1.5,
            "price": -125
          },
          "betrivers": {
            "line": 1.5,
            "price": -136
          },
          "pmu_fr": {
            "line": 1.5,
            "price": -159
          },
          "unibet_se": {
            "line": 1.5,
            "price": -136
          },
          "leovegas_se": {
            "line": 1.5,
            "price": -137
          },
          "unibet_nl": {
            "line": 1.5,
            "price": -136
          }
        },
        "Detroit Tigers": {
          "fanduel": {
            "line": -1.5,
            "price": -102
          },
          "fanatics": {
            "line": -1.5,
            "price": 105
          },
          "sport888": {
            "line": -1.5,
            "price": 100
          },
          "mybookieag": {
            "line": -1.5,
            "price": 100
          },
          "nordicbet": {
            "line": -1.5,
            "price": -103
          },
          "betsson": {
            "line": -1.5,
            "price": -103
          },
          "onexbet": {
            "line": -1.5,
            "price": 112
          },
          "draftkings": {
            "line": -1.5,
            "price": 102
          },
          "pinnacle": {
            "line": -1.5,
            "price": 107
          },
          "bovada": {
            "line": -1.5,
            "price": 105
          },
          "betrivers": {
            "line": -1.5,
            "price": 110
          },
          "pmu_fr": {
            "line": -1.5,
            "price": -106
          },
          "unibet_se": {
            "line": -1.5,
            "price": 110
          },
          "leovegas_se": {
            "line": -1.5,
            "price": 108
          },
          "unibet_nl": {
            "line": -1.5,
            "price": 110
          }
        }
      },
      "totals": {
        "Over": {
          "fanduel": {
            "line": 7.0,
            "price": 100
          },
          "fanatics": {
            "line": 7.0,
            "price": 100
          },
          "sport888": {
            "line": 6.5,
            "price": -133
          },
          "mybookieag": {
            "line": 7.0,
            "price": -103
          },
          "nordicbet": {
            "line": 7.0,
            "price": -111
          },
          "betsson": {
            "line": 7.0,
            "price": -111
          },
          "onexbet": {
            "line": 6.5,
            "price": -124
          },
          "draftkings": {
            "line": 7.0,
            "price": -102
          },
          "pinnacle": {
            "line": 7.0,
            "price": 100
          },
          "bovada": {
            "line": 7.0,
            "price": 100
          },
          "betrivers": {
            "line": 7.0,
            "price": 102
          },
          "pmu_fr": {
            "line": 7.0,
            "price": -113
          }
        },
        "Under": {
          "fanduel": {
            "line": 7.0,
            "price": -122
          },
          "fanatics": {
            "line": 7.0,
            "price": -120
          },
          "sport888": {
            "line": 6.5,
            "price": 105
          },
          "mybookieag": {
            "line": 7.0,
            "price": -119
          },
          "nordicbet": {
            "line": 7.0,
            "price": -116
          },
          "betsson": {
            "line": 7.0,
            "price": -116
          },
          "onexbet": {
            "line": 6.5,
            "price": 115
          },
          "draftkings": {
            "line": 7.0,
            "price": -118
          },
          "pinnacle": {
            "line": 7.0,
            "price": -115
          },
          "bovada": {
            "line": 7.0,
            "price": -120
          },
          "betrivers": {
            "line": 7.0,
            "price": -127
          },
          "pmu_fr": {
            "line": 7.0,
            "price": -148
          }
        }
      },
      "splits": {},
      "injuries": {
        "has_major_injury": 0.0,
        "home_injury_score": 0.0,
        "away_injury_score": 0.0,
        "injured_players": []
      }
    },
    {
      "timestamp": "2026-05-04_08-07-59",
      "hours_to_game": 14.538254102222222,
      "h2h": {
        "Boston Red Sox": {
          "fanduel": 190,
          "fanatics": 185,
          "unibet_fr": 180,
          "sport888": 195,
          "winamax_fr": 175,
          "mybookieag": 195,
          "nordicbet": 184,
          "winamax_de": 190,
          "betsson": 184,
          "onexbet": 192,
          "williamhill": 190,
          "marathonbet": 183,
          "draftkings": 194,
          "pinnacle": 194,
          "bovada": 190,
          "betrivers": 195,
          "unibet_se": 195,
          "leovegas_se": 195,
          "unibet_nl": 195,
          "matchbook": 205,
          "betmgm": 190,
          "lowvig": 191,
          "betonlineag": 191,
          "williamhill_us": 196,
          "gtbets": 188,
          "betus": 185,
          "betanysports": 183,
          "tipico_de": 200,
          "betfair_ex_eu": 200,
          "coolbet": 193,
          "everygame": 210
        },
        "Detroit Tigers": {
          "fanduel": -230,
          "fanatics": -225,
          "unibet_fr": -256,
          "sport888": -250,
          "winamax_fr": -263,
          "mybookieag": -233,
          "nordicbet": -233,
          "winamax_de": -244,
          "betsson": -233,
          "onexbet": -211,
          "williamhill": -250,
          "marathonbet": -233,
          "draftkings": -240,
          "pinnacle": -219,
          "bovada": -230,
          "betrivers": -250,
          "unibet_se": -240,
          "leovegas_se": -245,
          "unibet_nl": -240,
          "matchbook": -217,
          "betmgm": -235,
          "lowvig": -213,
          "betonlineag": -213,
          "williamhill_us": -240,
          "gtbets": -213,
          "betus": -213,
          "betanysports": -223,
          "tipico_de": -270,
          "betfair_ex_eu": -208,
          "coolbet": -244,
          "everygame": -240
        }
      },
      "spreads": {
        "Boston Red Sox": {
          "fanduel": {
            "line": 1.5,
            "price": -120
          },
          "fanatics": {
            "line": 1.5,
            "price": -125
          },
          "sport888": {
            "line": 1.5,
            "price": -125
          },
          "mybookieag": {
            "line": 1.5,
            "price": -119
          },
          "nordicbet": {
            "line": 1.5,
            "price": -125
          },
          "betsson": {
            "line": 1.5,
            "price": -125
          },
          "onexbet": {
            "line": 1.5,
            "price": -120
          },
          "draftkings": {
            "line": 1.5,
            "price": -122
          },
          "pinnacle": {
            "line": 1.5,
            "price": -119
          },
          "bovada": {
            "line": 1.5,
            "price": -120
          },
          "betrivers": {
            "line": 1.5,
            "price": -124
          },
          "pmu_fr": {
            "line": 1.5,
            "price": -143
          },
          "unibet_se": {
            "line": 1.5,
            "price": -122
          },
          "leovegas_se": {
            "line": 1.5,
            "price": -125
          },
          "unibet_nl": {
            "line": 1.5,
            "price": -122
          },
          "matchbook": {
            "line": 1.5,
            "price": -115
          },
          "betmgm": {
            "line": 1.5,
            "price": -120
          },
          "lowvig": {
            "line": 1.5,
            "price": -126
          },
          "betonlineag": {
            "line": 1.5,
            "price": -128
          },
          "williamhill_us": {
            "line": 1.5,
            "price": -120
          },
          "gtbets": {
            "line": 1.5,
            "price": -128
          },
          "betus": {
            "line": 1.5,
            "price": -120
          },
          "betanysports": {
            "line": 1.5,
            "price": -121
          },
          "coolbet": {
            "line": 1.5,
            "price": -118
          },
          "everygame": {
            "line": 1.5,
            "price": -120
          }
        },
        "Detroit Tigers": {
          "fanduel": {
            "line": -1.5,
            "price": 100
          },
          "fanatics": {
            "line": -1.5,
            "price": 105
          },
          "sport888": {
            "line": -1.5,
            "price": 100
          },
          "mybookieag": {
            "line": -1.5,
            "price": -101
          },
          "nordicbet": {
            "line": -1.5,
            "price": -103
          },
          "betsson": {
            "line": -1.5,
            "price": -103
          },
          "onexbet": {
            "line": -1.5,
            "price": 110
          },
          "draftkings": {
            "line": -1.5,
            "price": 102
          },
          "pinnacle": {
            "line": -1.5,
            "price": 105
          },
          "bovada": {
            "line": -1.5,
            "price": 100
          },
          "betrivers": {
            "line": -1.5,
            "price": 100
          },
          "pmu_fr": {
            "line": -1.5,
            "price": -114
          },
          "unibet_se": {
            "line": -1.5,
            "price": 102
          },
          "leovegas_se": {
            "line": -1.5,
            "price": 100
          },
          "unibet_nl": {
            "line": -1.5,
            "price": 102
          },
          "matchbook": {
            "line": -1.5,
            "price": 106
          },
          "betmgm": {
            "line": -1.5,
            "price": 100
          },
          "lowvig": {
            "line": -1.5,
            "price": 111
          },
          "betonlineag": {
            "line": -1.5,
            "price": 108
          },
          "williamhill_us": {
            "line": -1.5,
            "price": 100
          },
          "gtbets": {
            "line": -1.5,
            "price": 108
          },
          "betus": {
            "line": -1.5,
            "price": 100
          },
          "betanysports": {
            "line": -1.5,
            "price": 101
          },
          "coolbet": {
            "line": -1.5,
            "price": -104
          },
          "everygame": {
            "line": -1.5,
            "price": 100
          }
        }
      },
      "totals": {
        "Over": {
          "fanduel": {
            "line": 7.0,
            "price": -102
          },
          "fanatics": {
            "line": 7.0,
            "price": -105
          },
          "sport888": {
            "line": 6.5,
            "price": -133
          },
          "mybookieag": {
            "line": 7.0,
            "price": 100
          },
          "nordicbet": {
            "line": 7.0,
            "price": -111
          },
          "betsson": {
            "line": 7.0,
            "price": -111
          },
          "onexbet": {
            "line": 6.5,
            "price": -123
          },
          "draftkings": {
            "line": 7.0,
            "price": -102
          },
          "pinnacle": {
            "line": 7.0,
            "price": 100
          },
          "bovada": {
            "line": 7.0,
            "price": 100
          },
          "betrivers": {
            "line": 7.0,
            "price": 102
          },
          "pmu_fr": {
            "line": 7.0,
            "price": -113
          },
          "matchbook": {
            "line": 6.5,
            "price": -125
          },
          "betmgm": {
            "line": 7.0,
            "price": -102
          },
          "lowvig": {
            "line": 7.0,
            "price": -104
          },
          "betonlineag": {
            "line": 7.0,
            "price": -107
          },
          "williamhill_us": {
            "line": 7.0,
            "price": 100
          },
          "gtbets": {
            "line": 7.0,
            "price": -107
          },
          "betus": {
            "line": 7.0,
            "price": -105
          },
          "betanysports": {
            "line": 7.0,
            "price": -107
          },
          "tipico_de": {
            "line": 7.0,
            "price": -118
          },
          "coolbet": {
            "line": 7.0,
            "price": 100
          },
          "everygame": {
            "line": 7.0,
            "price": 100
          }
        },
        "Under": {
          "fanduel": {
            "line": 7.0,
            "price": -120
          },
          "fanatics": {
            "line": 7.0,
            "price": -115
          },
          "sport888": {
            "line": 6.5,
            "price": 105
          },
          "mybookieag": {
            "line": 7.0,
            "price": -122
          },
          "nordicbet": {
            "line": 7.0,
            "price": -116
          },
          "betsson": {
            "line": 7.0,
            "price": -116
          },
          "onexbet": {
            "line": 6.5,
            "price": 113
          },
          "draftkings": {
            "line": 7.0,
            "price": -118
          },
          "pinnacle": {
            "line": 7.0,
            "price": -115
          },
          "bovada": {
            "line": 7.0,
            "price": -120
          },
          "betrivers": {
            "line": 7.0,
            "price": -127
          },
          "pmu_fr": {
            "line": 7.0,
            "price": -148
          },
          "matchbook": {
            "line": 6.5,
            "price": 114
          },
          "betmgm": {
            "line": 7.0,
            "price": -118
          },
          "lowvig": {
            "line": 7.0,
            "price": -110
          },
          "betonlineag": {
            "line": 7.0,
            "price": -113
          },
          "williamhill_us": {
            "line": 7.0,
            "price": -120
          },
          "gtbets": {
            "line": 7.0,
            "price": -113
          },
          "betus": {
            "line": 7.0,
            "price": -115
          },
          "betanysports": {
            "line": 7.0,
            "price": -113
          },
          "tipico_de": {
            "line": 7.0,
            "price": -118
          },
          "coolbet": {
            "line": 7.0,
            "price": -122
          },
          "everygame": {
            "line": 7.0,
            "price": -120
          }
        }
      },
      "splits": {},
      "injuries": {
        "has_major_injury": 0.0,
        "home_injury_score": 0.0,
        "away_injury_score": 0.0,
        "injured_players": []
      }
    },
    {
      "timestamp": "2026-05-04_15-33-10",
      "hours_to_game": 7.1202901125,
      "h2h": {
        "Boston Red Sox": {
          "fanduel": 168,
          "fanatics": 165,
          "unibet_fr": 160,
          "sport888": 165,
          "winamax_fr": 160,
          "mybookieag": 165,
          "nordicbet": 157,
          "winamax_de": 165,
          "betsson": 168,
          "onexbet": 174,
          "williamhill": 160,
          "marathonbet": 162,
          "draftkings": 169,
          "pinnacle": 177,
          "bovada": 167,
          "betrivers": 175,
          "unibet_se": 180,
          "leovegas_se": 180,
          "unibet_nl": 180,
          "matchbook": 174,
          "betmgm": 165,
          "lowvig": 171,
          "betonlineag": 171,
          "williamhill_us": 162,
          "gtbets": 170,
          "betus": 166,
          "tipico_de": 170,
          "betfair_ex_eu": 180,
          "everygame": 170
        },
        "Detroit Tigers": {
          "fanduel": -200,
          "fanatics": -200,
          "unibet_fr": -217,
          "sport888": -213,
          "winamax_fr": -213,
          "mybookieag": -196,
          "nordicbet": -196,
          "winamax_de": -208,
          "betsson": -213,
          "onexbet": -190,
          "williamhill": -200,
          "marathonbet": -204,
          "draftkings": -207,
          "pinnacle": -194,
          "bovada": -204,
          "betrivers": -225,
          "unibet_se": -220,
          "leovegas_se": -225,
          "unibet_nl": -220,
          "matchbook": -185,
          "betmgm": -200,
          "lowvig": -190,
          "betonlineag": -190,
          "williamhill_us": -195,
          "gtbets": -190,
          "betus": -190,
          "tipico_de": -222,
          "betfair_ex_eu": -185,
          "everygame": -190
        }
      },
      "spreads": {
        "Boston Red Sox": {
          "fanduel": {
            "line": 1.5,
            "price": -130
          },
          "fanatics": {
            "line": 1.5,
            "price": -140
          },
          "sport888": {
            "line": 1.5,
            "price": -133
          },
          "mybookieag": {
            "line": 1.5,
            "price": -136
          },
          "nordicbet": {
            "line": 1.5,
            "price": -139
          },
          "betsson": {
            "line": 1.5,
            "price": -132
          },
          "onexbet": {
            "line": 1.5,
            "price": -131
          },
          "draftkings": {
            "line": 1.5,
            "price": -136
          },
          "pinnacle": {
            "line": 1.5,
            "price": -125
          },
          "bovada": {
            "line": 1.5,
            "price": -130
          },
          "betrivers": {
            "line": 1.5,
            "price": -134
          },
          "pmu_fr": {
            "line": 1.5,
            "price": -157
          },
          "unibet_se": {
            "line": 1.5,
            "price": -132
          },
          "leovegas_se": {
            "line": 1.5,
            "price": -136
          },
          "unibet_nl": {
            "line": 1.5,
            "price": -132
          },
          "matchbook": {
            "line": 1.5,
            "price": -128
          },
          "betmgm": {
            "line": 1.5,
            "price": -145
          },
          "lowvig": {
            "line": 1.5,
            "price": -138
          },
          "betonlineag": {
            "line": 1.5,
            "price": -140
          },
          "williamhill_us": {
            "line": 1.5,
            "price": -140
          },
          "gtbets": {
            "line": 1.5,
            "price": -140
          },
          "betus": {
            "line": 1.5,
            "price": -140
          },
          "betanysports": {
            "line": 2.5,
            "price": -195
          },
          "everygame": {
            "line": 1.5,
            "price": -140
          }
        },
        "Detroit Tigers": {
          "fanduel": {
            "line": -1.5,
            "price": 108
          },
          "fanatics": {
            "line": -1.5,
            "price": 115
          },
          "sport888": {
            "line": -1.5,
            "price": 105
          },
          "mybookieag": {
            "line": -1.5,
            "price": 115
          },
          "nordicbet": {
            "line": -1.5,
            "price": 107
          },
          "betsson": {
            "line": -1.5,
            "price": 102
          },
          "onexbet": {
            "line": -1.5,
            "price": 121
          },
          "draftkings": {
            "line": -1.5,
            "price": 113
          },
          "pinnacle": {
            "line": -1.5,
            "price": 113
          },
          "bovada": {
            "line": -1.5,
            "price": 110
          },
          "betrivers": {
            "line": -1.5,
            "price": 108
          },
          "pmu_fr": {
            "line": -1.5,
            "price": -106
          },
          "unibet_se": {
            "line": -1.5,
            "price": 110
          },
          "leovegas_se": {
            "line": -1.5,
            "price": 107
          },
          "unibet_nl": {
            "line": -1.5,
            "price": 110
          },
          "matchbook": {
            "line": -1.5,
            "price": 118
          },
          "betmgm": {
            "line": -1.5,
            "price": 120
          },
          "lowvig": {
            "line": -1.5,
            "price": 122
          },
          "betonlineag": {
            "line": -1.5,
            "price": 120
          },
          "williamhill_us": {
            "line": -1.5,
            "price": 118
          },
          "gtbets": {
            "line": -1.5,
            "price": 120
          },
          "betus": {
            "line": -1.5,
            "price": 120
          },
          "betanysports": {
            "line": -2.5,
            "price": 160
          },
          "everygame": {
            "line": -1.5,
            "price": 120
          }
        }
      },
      "totals": {
        "Over": {
          "fanduel": {
            "line": 7.0,
            "price": -105
          },
          "fanatics": {
            "line": 7.0,
            "price": -105
          },
          "sport888": {
            "line": 6.5,
            "price": -137
          },
          "mybookieag": {
            "line": 7.0,
            "price": -104
          },
          "nordicbet": {
            "line": 7.0,
            "price": -114
          },
          "betsson": {
            "line": 7.0,
            "price": -114
          },
          "onexbet": {
            "line": 6.5,
            "price": -131
          },
          "draftkings": {
            "line": 7.0,
            "price": -105
          },
          "pinnacle": {
            "line": 7.0,
            "price": -105
          },
          "bovada": {
            "line": 7.0,
            "price": -110
          },
          "betrivers": {
            "line": 7.0,
            "price": -104
          },
          "pmu_fr": {
            "line": 7.0,
            "price": -118
          },
          "matchbook": {
            "line": 6.5,
            "price": -135
          },
          "betmgm": {
            "line": 7.0,
            "price": 100
          },
          "lowvig": {
            "line": 7.0,
            "price": -103
          },
          "betonlineag": {
            "line": 7.0,
            "price": -106
          },
          "williamhill_us": {
            "line": 7.0,
            "price": -105
          },
          "gtbets": {
            "line": 7.0,
            "price": -106
          },
          "betus": {
            "line": 7.0,
            "price": -105
          },
          "tipico_de": {
            "line": 7.0,
            "price": -118
          },
          "everygame": {
            "line": 7.0,
            "price": 100
          }
        },
        "Under": {
          "fanduel": {
            "line": 7.0,
            "price": -115
          },
          "fanatics": {
            "line": 7.0,
            "price": -115
          },
          "sport888": {
            "line": 6.5,
            "price": 110
          },
          "mybookieag": {
            "line": 7.0,
            "price": -118
          },
          "nordicbet": {
            "line": 7.0,
            "price": -114
          },
          "betsson": {
            "line": 7.0,
            "price": -114
          },
          "onexbet": {
            "line": 6.5,
            "price": 121
          },
          "draftkings": {
            "line": 7.0,
            "price": -115
          },
          "pinnacle": {
            "line": 7.0,
            "price": -107
          },
          "bovada": {
            "line": 7.0,
            "price": -110
          },
          "betrivers": {
            "line": 7.0,
            "price": -121
          },
          "pmu_fr": {
            "line": 7.0,
            "price": -141
          },
          "matchbook": {
            "line": 6.5,
            "price": 122
          },
          "betmgm": {
            "line": 7.0,
            "price": -120
          },
          "lowvig": {
            "line": 7.0,
            "price": -112
          },
          "betonlineag": {
            "line": 7.0,
            "price": -114
          },
          "williamhill_us": {
            "line": 7.0,
            "price": -115
          },
          "gtbets": {
            "line": 7.0,
            "price": -114
          },
          "betus": {
            "line": 7.0,
            "price": -115
          },
          "tipico_de": {
            "line": 7.0,
            "price": -118
          },
          "everygame": {
            "line": 7.0,
            "price": -120
          }
        }
      },
      "splits": {},
      "injuries": {
        "has_major_injury": 0.0,
        "home_injury_score": 0.0,
        "away_injury_score": 0.0,
        "injured_players": []
      }
    },
    {
      "timestamp": "2026-05-04_20-49-09",
      "hours_to_game": 1.3519893044444444,
      "h2h": {
        "Boston Red Sox": {
          "fanduel": -116,
          "fanatics": -120,
          "unibet_fr": -118,
          "sport888": -118,
          "winamax_fr": -122,
          "mybookieag": -115,
          "nordicbet": -120,
          "winamax_de": -119,
          "betsson": 168,
          "onexbet": -113,
          "williamhill": -110,
          "marathonbet": -120,
          "draftkings": -118,
          "pinnacle": -115,
          "bovada": -121,
          "betrivers": -120,
          "unibet_se": -117,
          "leovegas_se": -118,
          "unibet_nl": -117,
          "matchbook": -111,
          "betmgm": -120,
          "lowvig": -117,
          "betonlineag": -117,
          "williamhill_us": -120,
          "gtbets": -117,
          "betus": -113,
          "tipico_de": -115,
          "betfair_ex_eu": -112,
          "everygame": -116
        },
        "Detroit Tigers": {
          "fanduel": -102,
          "fanatics": 100,
          "unibet_fr": -104,
          "sport888": -110,
          "winamax_fr": -109,
          "mybookieag": -102,
          "nordicbet": -102,
          "winamax_de": -106,
          "betsson": -213,
          "onexbet": 104,
          "williamhill": -110,
          "marathonbet": -102,
          "draftkings": -102,
          "pinnacle": 106,
          "bovada": 101,
          "betrivers": -105,
          "unibet_se": -103,
          "leovegas_se": -104,
          "unibet_nl": -103,
          "matchbook": 108,
          "betmgm": 100,
          "lowvig": 106,
          "betonlineag": 106,
          "williamhill_us": 100,
          "gtbets": 107,
          "betus": 103,
          "tipico_de": -111,
          "betfair_ex_eu": 108,
          "everygame": 106
        }
      },
      "spreads": {
        "Boston Red Sox": {
          "fanduel": {
            "line": -1.5,
            "price": 142
          },
          "fanatics": {
            "line": -1.5,
            "price": 140
          },
          "sport888": {
            "line": -1.5,
            "price": 140
          },
          "mybookieag": {
            "line": -1.5,
            "price": 148
          },
          "nordicbet": {
            "line": -1.5,
            "price": 132
          },
          "betsson": {
            "line": 1.5,
            "price": -132
          },
          "onexbet": {
            "line": -1.5,
            "price": 137
          },
          "draftkings": {
            "line": -1.5,
            "price": 135
          },
          "pinnacle": {
            "line": -1.5,
            "price": 150
          },
          "bovada": {
            "line": -1.5,
            "price": 145
          },
          "betrivers": {
            "line": -1.5,
            "price": 143
          },
          "pmu_fr": {
            "line": -1.0,
            "price": -103
          },
          "unibet_se": {
            "line": -1.0,
            "price": 114
          },
          "leovegas_se": {
            "line": -1.0,
            "price": 110
          },
          "unibet_nl": {
            "line": -1.0,
            "price": 114
          },
          "matchbook": {
            "line": -1.5,
            "price": 156
          },
          "betmgm": {
            "line": -1.5,
            "price": 140
          },
          "lowvig": {
            "line": 1.5,
            "price": -226
          },
          "betonlineag": {
            "line": 1.5,
            "price": -230
          },
          "williamhill_us": {
            "line": -1.5,
            "price": 143
          },
          "gtbets": {
            "line": 1.5,
            "price": -230
          },
          "betus": {
            "line": 1.5,
            "price": -230
          },
          "betanysports": {
            "line": 2.5,
            "price": -370
          },
          "everygame": {
            "line": 1.5,
            "price": -225
          }
        },
        "Detroit Tigers": {
          "fanduel": {
            "line": 1.5,
            "price": -172
          },
          "fanatics": {
            "line": 1.5,
            "price": -170
          },
          "sport888": {
            "line": 1.5,
            "price": -175
          },
          "mybookieag": {
            "line": 1.5,
            "price": -174
          },
          "nordicbet": {
            "line": 1.5,
            "price": -172
          },
          "betsson": {
            "line": -1.5,
            "price": 102
          },
          "onexbet": {
            "line": 1.5,
            "price": -149
          },
          "draftkings": {
            "line": 1.5,
            "price": -163
          },
          "pinnacle": {
            "line": 1.5,
            "price": -168
          },
          "bovada": {
            "line": 1.5,
            "price": -170
          },
          "betrivers": {
            "line": 1.5,
            "price": -180
          },
          "pmu_fr": {
            "line": 1.0,
            "price": -165
          },
          "unibet_se": {
            "line": 1.0,
            "price": -137
          },
          "leovegas_se": {
            "line": 1.0,
            "price": -141
          },
          "unibet_nl": {
            "line": 1.0,
            "price": -137
          },
          "matchbook": {
            "line": 1.5,
            "price": -161
          },
          "betmgm": {
            "line": 1.5,
            "price": -170
          },
          "lowvig": {
            "line": -1.5,
            "price": 196
          },
          "betonlineag": {
            "line": -1.5,
            "price": 192
          },
          "williamhill_us": {
            "line": 1.5,
            "price": -170
          },
          "gtbets": {
            "line": -1.5,
            "price": 192
          },
          "betus": {
            "line": -1.5,
            "price": 196
          },
          "betanysports": {
            "line": -2.5,
            "price": 280
          },
          "everygame": {
            "line": -1.5,
            "price": 185
          }
        }
      },
      "totals": {
        "Over": {
          "fanduel": {
            "line": 8.0,
            "price": -120
          },
          "fanatics": {
            "line": 8.5,
            "price": 100
          },
          "sport888": {
            "line": 8.5,
            "price": 100
          },
          "mybookieag": {
            "line": 8.0,
            "price": -114
          },
          "nordicbet": {
            "line": 7.0,
            "price": -208
          },
          "betsson": {
            "line": 7.0,
            "price": -114
          },
          "onexbet": {
            "line": 8.5,
            "price": 105
          },
          "draftkings": {
            "line": 8.0,
            "price": -118
          },
          "pinnacle": {
            "line": 8.0,
            "price": -114
          },
          "bovada": {
            "line": 8.0,
            "price": -120
          },
          "betrivers": {
            "line": 8.0,
            "price": -114
          },
          "pmu_fr": {
            "line": 8.0,
            "price": -130
          },
          "matchbook": {
            "line": 8.5,
            "price": 106
          },
          "betmgm": {
            "line": 8.0,
            "price": -120
          },
          "lowvig": {
            "line": 8.5,
            "price": -102
          },
          "betonlineag": {
            "line": 8.5,
            "price": -105
          },
          "williamhill_us": {
            "line": 8.0,
            "price": -115
          },
          "gtbets": {
            "line": 8.5,
            "price": -105
          },
          "betus": {
            "line": 8.5,
            "price": -105
          },
          "tipico_de": {
            "line": 8.5,
            "price": -105
          },
          "everygame": {
            "line": 8.0,
            "price": -125
          }
        },
        "Under": {
          "fanduel": {
            "line": 8.0,
            "price": -102
          },
          "fanatics": {
            "line": 8.5,
            "price": -120
          },
          "sport888": {
            "line": 8.5,
            "price": -125
          },
          "mybookieag": {
            "line": 8.0,
            "price": -108
          },
          "nordicbet": {
            "line": 7.0,
            "price": 156
          },
          "betsson": {
            "line": 7.0,
            "price": -114
          },
          "onexbet": {
            "line": 8.5,
            "price": -114
          },
          "draftkings": {
            "line": 8.0,
            "price": -102
          },
          "pinnacle": {
            "line": 8.0,
            "price": 101
          },
          "bovada": {
            "line": 8.0,
            "price": 100
          },
          "betrivers": {
            "line": 8.0,
            "price": -109
          },
          "pmu_fr": {
            "line": 8.0,
            "price": -125
          },
          "matchbook": {
            "line": 8.5,
            "price": -109
          },
          "betmgm": {
            "line": 8.0,
            "price": 100
          },
          "lowvig": {
            "line": 8.5,
            "price": -113
          },
          "betonlineag": {
            "line": 8.5,
            "price": -115
          },
          "williamhill_us": {
            "line": 8.0,
            "price": -105
          },
          "gtbets": {
            "line": 8.5,
            "price": -115
          },
          "betus": {
            "line": 8.5,
            "price": -115
          },
          "tipico_de": {
            "line": 8.5,
            "price": -133
          },
          "everygame": {
            "line": 8.0,
            "price": 105
          }
        }
      },
      "splits": {}
    }
  ]
}