{
  "event_id": "55fa28ecac0b985cde7ea3ed079986e0",
  "sport_key": "baseball_mlb",
  "home_team": "Los Angeles Dodgers",
  "away_team": "Chicago Cubs",
  "commence_time": "2026-04-25T02:16:00Z",
  "snapshots": [
    {
      "timestamp": "2026-04-25T00:00:00Z",
      "hours_to_game": 2.2666666666666666,
      "h2h": {
        "Chicago Cubs": {
          "fanduel": 138,
          "gtbets": 136,
          "sport888": 130,
          "coolbet": 133,
          "betonlineag": 134,
          "lowvig": 134,
          "unibet_fr": 130,
          "fanatics": 130,
          "nordicbet": 133,
          "betsson": 133,
          "onexbet": 141,
          "winamax_fr": 125,
          "winamax_de": 125,
          "williamhill_us": 135,
          "draftkings": 129,
          "betus": 133,
          "williamhill": 130,
          "marathonbet": 134,
          "unibet_nl": 138,
          "leovegas_se": 135,
          "betrivers": 135,
          "unibet_se": 138,
          "betmgm": 135,
          "bovada": 133,
          "pinnacle": 139,
          "mybookieag": 133,
          "matchbook": 142,
          "tipico_de": 130,
          "betfair_ex_eu": 142
        },
        "Los Angeles Dodgers": {
          "fanduel": -164,
          "gtbets": -148,
          "sport888": -161,
          "coolbet": -164,
          "betonlineag": -148,
          "lowvig": -148,
          "unibet_fr": -159,
          "fanatics": -155,
          "nordicbet": -164,
          "betsson": -164,
          "onexbet": -154,
          "winamax_fr": -167,
          "winamax_de": -161,
          "williamhill_us": -160,
          "draftkings": -156,
          "betus": -148,
          "williamhill": -162,
          "marathonbet": -167,
          "unibet_nl": -165,
          "leovegas_se": -167,
          "betrivers": -167,
          "unibet_se": -165,
          "betmgm": -160,
          "bovada": -159,
          "pinnacle": -151,
          "mybookieag": -156,
          "matchbook": -147,
          "tipico_de": -167,
          "betfair_ex_eu": -147
        }
      },
      "spreads": {
        "Chicago Cubs": {
          "fanduel": {
            "line": 1.5,
            "price": -154
          },
          "gtbets": {
            "line": 1.5,
            "price": -150
          },
          "sport888": {
            "line": 1.5,
            "price": -154
          },
          "coolbet": {
            "line": 1.5,
            "price": -152
          },
          "betonlineag": {
            "line": 1.5,
            "price": -150
          },
          "lowvig": {
            "line": 1.5,
            "price": -149
          },
          "fanatics": {
            "line": 1.5,
            "price": -150
          },
          "nordicbet": {
            "line": 1.5,
            "price": -152
          },
          "betsson": {
            "line": 1.5,
            "price": -152
          },
          "onexbet": {
            "line": 1.5,
            "price": -143
          },
          "williamhill_us": {
            "line": 1.5,
            "price": -155
          },
          "draftkings": {
            "line": 1.5,
            "price": -156
          },
          "betus": {
            "line": 1.5,
            "price": -150
          },
          "unibet_nl": {
            "line": 1.0,
            "price": -108
          },
          "leovegas_se": {
            "line": 1.0,
            "price": -110
          },
          "pmu_fr": {
            "line": 1.0,
            "price": -125
          },
          "betrivers": {
            "line": 1.5,
            "price": -162
          },
          "unibet_se": {
            "line": 1.0,
            "price": -108
          },
          "betmgm": {
            "line": 1.5,
            "price": -150
          },
          "bovada": {
            "line": 1.5,
            "price": -150
          },
          "pinnacle": {
            "line": 1.5,
            "price": -146
          },
          "betanysports": {
            "line": 2.5,
            "price": -230
          },
          "mybookieag": {
            "line": 1.5,
            "price": -148
          },
          "matchbook": {
            "line": 1.5,
            "price": -141
          }
        },
        "Los Angeles Dodgers": {
          "fanduel": {
            "line": -1.5,
            "price": 128
          },
          "gtbets": {
            "line": -1.5,
            "price": 130
          },
          "sport888": {
            "line": -1.5,
            "price": 125
          },
          "coolbet": {
            "line": -1.5,
            "price": 123
          },
          "betonlineag": {
            "line": -1.5,
            "price": 130
          },
          "lowvig": {
            "line": -1.5,
            "price": 132
          },
          "fanatics": {
            "line": -1.5,
            "price": 125
          },
          "nordicbet": {
            "line": -1.5,
            "price": 117
          },
          "betsson": {
            "line": -1.5,
            "price": 117
          },
          "onexbet": {
            "line": -1.5,
            "price": 131
          },
          "williamhill_us": {
            "line": -1.5,
            "price": 130
          },
          "draftkings": {
            "line": -1.5,
            "price": 129
          },
          "betus": {
            "line": -1.5,
            "price": 130
          },
          "unibet_nl": {
            "line": -1.0,
            "price": -113
          },
          "leovegas_se": {
            "line": -1.0,
            "price": -115
          },
          "pmu_fr": {
            "line": -1.0,
            "price": -132
          },
          "betrivers": {
            "line": -1.5,
            "price": 128
          },
          "unibet_se": {
            "line": -1.0,
            "price": -113
          },
          "betmgm": {
            "line": -1.5,
            "price": 125
          },
          "bovada": {
            "line": -1.5,
            "price": 130
          },
          "pinnacle": {
            "line": -1.5,
            "price": 132
          },
          "betanysports": {
            "line": -2.5,
            "price": 185
          },
          "mybookieag": {
            "line": -1.5,
            "price": 120
          },
          "matchbook": {
            "line": -1.5,
            "price": 134
          }
        }
      },
      "totals": {
        "Over": {
          "fanduel": {
            "line": 9.0,
            "price": -108
          },
          "gtbets": {
            "line": 9.0,
            "price": -107
          },
          "sport888": {
            "line": 8.5,
            "price": -137
          },
          "coolbet": {
            "line": 9.0,
            "price": -105
          },
          "betonlineag": {
            "line": 9.0,
            "price": -107
          },
          "lowvig": {
            "line": 9.0,
            "price": -104
          },
          "fanatics": {
            "line": 9.0,
            "price": -105
          },
          "nordicbet": {
            "line": 9.0,
            "price": -116
          },
          "betsson": {
            "line": 9.0,
            "price": -116
          },
          "onexbet": {
            "line": 8.5,
            "price": -123
          },
          "williamhill_us": {
            "line": 9.0,
            "price": -110
          },
          "draftkings": {
            "line": 9.0,
            "price": -110
          },
          "betus": {
            "line": 9.0,
            "price": -110
          },
          "pmu_fr": {
            "line": 9.0,
            "price": -129
          },
          "betrivers": {
            "line": 9.0,
            "price": -110
          },
          "betmgm": {
            "line": 9.0,
            "price": -110
          },
          "bovada": {
            "line": 9.0,
            "price": -105
          },
          "pinnacle": {
            "line": 9.0,
            "price": -101
          },
          "mybookieag": {
            "line": 9.0,
            "price": -111
          },
          "matchbook": {
            "line": 8.5,
            "price": -125
          },
          "tipico_de": {
            "line": 9.5,
            "price": -105
          }
        },
        "Under": {
          "fanduel": {
            "line": 9.0,
            "price": -112
          },
          "gtbets": {
            "line": 9.0,
            "price": -113
          },
          "sport888": {
            "line": 8.5,
            "price": 110
          },
          "coolbet": {
            "line": 9.0,
            "price": -115
          },
          "betonlineag": {
            "line": 9.0,
            "price": -113
          },
          "lowvig": {
            "line": 9.0,
            "price": -110
          },
          "fanatics": {
            "line": 9.0,
            "price": -115
          },
          "nordicbet": {
            "line": 9.0,
            "price": -111
          },
          "betsson": {
            "line": 9.0,
            "price": -111
          },
          "onexbet": {
            "line": 8.5,
            "price": 113
          },
          "williamhill_us": {
            "line": 9.0,
            "price": -110
          },
          "draftkings": {
            "line": 9.0,
            "price": -110
          },
          "betus": {
            "line": 9.0,
            "price": -110
          },
          "pmu_fr": {
            "line": 9.0,
            "price": -129
          },
          "betrivers": {
            "line": 9.0,
            "price": -112
          },
          "betmgm": {
            "line": 9.0,
            "price": -110
          },
          "bovada": {
            "line": 9.0,
            "price": -115
          },
          "pinnacle": {
            "line": 9.0,
            "price": -111
          },
          "mybookieag": {
            "line": 9.0,
            "price": -110
          },
          "matchbook": {
            "line": 8.5,
            "price": 120
          },
          "tipico_de": {
            "line": 9.5,
            "price": -133
          }
        }
      },
      "splits": {}
    }
  ]
}